package_pku/__init__.py
package_pku/modul1.py
package_pku/modul2.py
package_pku/data/jup_start.cmd
package_pku-0.0.3.data/data/data/jup_start.cmd
package_pku-0.0.3.dist-info/METADATA
package_pku-0.0.3.dist-info/WHEEL
package_pku-0.0.3.dist-info/top_level.txt
package_pku-0.0.3.dist-info/RECORD
